error_parity/__init__.py
error_parity/_commons.py
error_parity/_version.py
error_parity/binarize.py
error_parity/classifiers.py
error_parity/cvxpy_utils.py
error_parity/evaluation.py
error_parity/pareto_curve.py
error_parity/plotting.py
error_parity/roc_utils.py
error_parity/threshold_optimizer.py
error_parity-0.3.12.dist-info/licenses/LICENSE
error_parity-0.3.12.dist-info/METADATA
error_parity-0.3.12.dist-info/WHEEL
error_parity-0.3.12.dist-info/top_level.txt
error_parity-0.3.12.dist-info/RECORD
