Metadata-Version: 2.4
Name: error-parity
Version: 0.3.12
Summary: Achieve error-rate parity between protected groups for any predictor
Author: AndreFCruz
License-Expression: MIT
Project-URL: homepage, https://github.com/socialfoundations/error-parity
Keywords: ml,optimization,fairness,error-parity,equal-odds
Classifier: Development Status :: 3 - Alpha
Classifier: Intended Audience :: Science/Research
Classifier: Topic :: Scientific/Engineering :: Artificial Intelligence
Classifier: Programming Language :: Python :: 3
Classifier: Programming Language :: Python :: 3.9
Classifier: Programming Language :: Python :: 3.10
Classifier: Programming Language :: Python :: 3.11
Classifier: Programming Language :: Python :: 3.12
Requires-Python: >=3.9
License-File: LICENSE
Requires-Dist: pandas
Requires-Dist: numpy<2.0.0
Requires-Dist: scipy
Requires-Dist: tqdm
Requires-Dist: scikit-learn>=1.2
Requires-Dist: cvxpy[clarabel,ecos]~=1.3.2
Requires-Dist: matplotlib
Requires-Dist: seaborn
Provides-Extra: test
Requires-Dist: pytest>=8.0; extra == "test"
Requires-Dist: coverage>=7.0; extra == "test"
Requires-Dist: folktables; extra == "test"
Requires-Dist: tqdm; extra == "test"
Requires-Dist: mypy; extra == "test"
Provides-Extra: dev
Requires-Dist: ipdb; extra == "dev"
Requires-Dist: notebook; extra == "dev"
Requires-Dist: folktables; extra == "dev"
Requires-Dist: hyperparameter-tuning; extra == "dev"
Provides-Extra: docs
Requires-Dist: sphinx; extra == "docs"
Requires-Dist: sphinx_rtd_theme; extra == "docs"
Requires-Dist: sphinx-autopackagesummary; extra == "docs"
Requires-Dist: myst-parser; extra == "docs"
Requires-Dist: sphinx-copybutton; extra == "docs"
Requires-Dist: readthedocs-sphinx-search; extra == "docs"
Requires-Dist: nbsphinx; extra == "docs"
Requires-Dist: sphinx_gallery; extra == "docs"
Requires-Dist: numpydoc; extra == "docs"
Requires-Dist: sphinx-autodoc-typehints; extra == "docs"
Requires-Dist: IPython; extra == "docs"
Requires-Dist: ipykernel; extra == "docs"
Provides-Extra: all
Requires-Dist: ipdb; extra == "all"
Requires-Dist: notebook; extra == "all"
Requires-Dist: folktables; extra == "all"
Requires-Dist: hyperparameter-tuning; extra == "all"
Requires-Dist: pytest>=8.0; extra == "all"
Requires-Dist: coverage>=7.0; extra == "all"
Requires-Dist: folktables; extra == "all"
Requires-Dist: tqdm; extra == "all"
Requires-Dist: mypy; extra == "all"
Requires-Dist: sphinx; extra == "all"
Requires-Dist: sphinx_rtd_theme; extra == "all"
Requires-Dist: sphinx-autopackagesummary; extra == "all"
Requires-Dist: myst-parser; extra == "all"
Requires-Dist: sphinx-copybutton; extra == "all"
Requires-Dist: readthedocs-sphinx-search; extra == "all"
Requires-Dist: nbsphinx; extra == "all"
Requires-Dist: sphinx_gallery; extra == "all"
Requires-Dist: numpydoc; extra == "all"
Requires-Dist: sphinx-autodoc-typehints; extra == "all"
Requires-Dist: IPython; extra == "all"
Requires-Dist: ipykernel; extra == "all"
Dynamic: license-file
